MANIFEST.in
README.rst
setup.cfg
setup.py
hexlet/__init__.py
hexlet/cli.py
hexlet/exceptions.py
hexlet/lesson_cli.py
hexlet/logger.py
hexlet/routes.py
hexlet/utils.py
hexlet.egg-info/PKG-INFO
hexlet.egg-info/SOURCES.txt
hexlet.egg-info/dependency_links.txt
hexlet.egg-info/entry_points.txt
hexlet.egg-info/requires.txt
hexlet.egg-info/top_level.txt
hexlet/commands/__init__.py
hexlet/commands/dist.py
hexlet/commands/exercise.py
hexlet/commands/lesson.py
hexlet/commands/shared.py
hexlet/data/locales/commands.en.yml
hexlet/data/locales/main.en.yml
hexlet/data/skeletons/lesson/.gitignore
hexlet/data/skeletons/lesson/lesson.yml
hexlet/data/skeletons/lesson/code/.Makefile.swp
hexlet/data/skeletons/lesson/code/.main.yml.swp
hexlet/data/skeletons/lesson/code/.readme.md.swp
hexlet/data/skeletons/lesson/code/Makefile
hexlet/data/skeletons/lesson/code/main.yml
hexlet/data/skeletons/lesson/code/readme.md
hexlet/data/skeletons/lesson/codex/.Makefile.swp
hexlet/data/skeletons/lesson/codex/.main.yml.swp
hexlet/data/skeletons/lesson/codex/Makefile
hexlet/data/skeletons/lesson/codex/main.yml
hexlet/data/skeletons/lesson/quiz/main.yml
hexlet/data/skeletons/lesson/terminal/Gruntfile.js
hexlet/data/skeletons/lesson/terminal/Makefile
hexlet/data/skeletons/lesson/terminal/bower.json
hexlet/data/skeletons/lesson/terminal/karma.conf.js
hexlet/data/skeletons/lesson/terminal/main.yml
hexlet/data/skeletons/lesson/terminal/package.json
hexlet/data/skeletons/lesson/terminal/test-main.js
hexlet/data/skeletons/lesson/terminal/js/terminal/setup.js
hexlet/data/skeletons/lesson/terminal/js/terminal/strings.js
hexlet/data/skeletons/lesson/theory/.main.md.swp
hexlet/data/skeletons/lesson/theory/.main.yml.swp
hexlet/data/skeletons/lesson/theory/.transcription.md.swp
hexlet/data/skeletons/lesson/theory/main.md
hexlet/data/skeletons/lesson/theory/main.yml
hexlet/data/skeletons/lesson/theory/transcription.md