Metadata-Version: 1.0
Name: hexlet
Version: 0.6.2
Summary: CLI for hexlet.io
Home-page: http://hexlet.io
Author: Kirill Mokevnin
Author-email: mokevnin@gmail.com
License: MIT
Platform: UNKNOWN
